yb/__init__.py
yb-0.0.3.dist-info/LICENSE
yb-0.0.3.dist-info/METADATA
yb-0.0.3.dist-info/WHEEL
yb-0.0.3.dist-info/top_level.txt
yb-0.0.3.dist-info/RECORD
